examplepy/__init__.py
examplepy/module1.py
exple_ppi_pakage2-0.1.0.dist-info/LICENSE
exple_ppi_pakage2-0.1.0.dist-info/METADATA
exple_ppi_pakage2-0.1.0.dist-info/WHEEL
exple_ppi_pakage2-0.1.0.dist-info/top_level.txt
exple_ppi_pakage2-0.1.0.dist-info/RECORD
