Metadata-Version: 2.1
Name: exple_ppi_pakage2
Version: 0.1.0
Summary: Example yPI (Python Package Index) Package
Home-page: https://github.com/tomchen/example_pypi_package
Author: Tom Cen
Author-email: tomhen.org@gmail.com
Project-URL: Source Code, https://github.com/tomchen/example_pypi_package
Keywords: exaple,pypi
Classifier: Development Status :: 5 - Production/Stable
Classifier: License :: OSI Approved :: MIT License
Classifier: Operating System :: OS Independent
Requires-Python: >=3.6
License-File: LICENSE
Provides-Extra: dev
Requires-Dist: check-manifest ; extra == 'dev'
